setup.py
icinga2_api/__init__.py
icinga2_api/api.py
icinga2_api/cmdline.py
icinga2_api/defaults.py
icinga2_api.egg-info/PKG-INFO
icinga2_api.egg-info/SOURCES.txt
icinga2_api.egg-info/dependency_links.txt
icinga2_api.egg-info/entry_points.txt
icinga2_api.egg-info/requires.txt
icinga2_api.egg-info/top_level.txt