Metadata-Version: 1.0
Name: icinga2-api
Version: 0.0.6
Summary: Python library and command-line support for the icinga2 API
Home-page: https://github.com/saurabh-hirani/icinga2_api
Author: Saurabh Hirani
Author-email: saurabh.hirani@gmail.com
License: MIT
Platform: UNKNOWN
